inventree_ft8/__init__.py
inventree_ft8/ft8_client.py
inventree_ft8/version.py
inventree_ft8/static/FT8Panel.js
inventree_ft8/static/assets/decode.wasm
inventree_ft8/static/assets/encode.wasm
inventree_ft8/static/assets/index.js
inventree_ft8/templates/plugin/ft8/console.html
inventree_ft8-0.0.1.dist-info/METADATA
inventree_ft8-0.0.1.dist-info/WHEEL
inventree_ft8-0.0.1.dist-info/entry_points.txt
inventree_ft8-0.0.1.dist-info/top_level.txt
inventree_ft8-0.0.1.dist-info/RECORD
