Metadata-Version: 2.4
Name: inventree-ft8
Version: 0.0.1
Summary: FT8 Client for InvenTree
Home-page: https://danebramage.org/git/
Author: Jordan Bush
Author-email: jordan@malmoset.com
License: MIT
Keywords: inventree ft8 client
Requires-Python: >=3.6
Dynamic: author
Dynamic: author-email
Dynamic: description
Dynamic: description-content-type
Dynamic: home-page
Dynamic: keywords
Dynamic: license
Dynamic: requires-python
Dynamic: summary
